camerafiles/CamOperation_class.py
camerafiles/camera.py
camerafiles/get_image.py
camerafiles/tools.py
functions/ArithmeticOperations.py
functions/Intensity.py
functions/ModelOperations.py
functions/Rejections.py
functions/calculation.py
functions/calibrate.py
functions/colorSpaceOperations.py
functions/contourAnalysis.py
functions/geometric.py
functions/imageArithmetics.py
functions/imageEnhancement.py
functions/imageFiltering.py
functions/plyTrigger.py
functions/roi.py
functions/template_matching.py
functions/visualization.py
backend_xyz12345-0.1.0.dist-info/METADATA
backend_xyz12345-0.1.0.dist-info/WHEEL
backend_xyz12345-0.1.0.dist-info/top_level.txt
backend_xyz12345-0.1.0.dist-info/RECORD
