Metadata-Version: 2.4
Name: backend_xyz12345
Version: 0.1.0
Summary: Add your description here
Requires-Python: >=3.10
Requires-Dist: fastapi>=0.115.13
Requires-Dist: matplotlib>=3.10.3
Requires-Dist: networkx>=3.4.2
Requires-Dist: opencv-python>=4.11.0.86
Requires-Dist: pillow>=11.2.1
Requires-Dist: pydantic>=2.11.7
Requires-Dist: scikit-image>=0.25.2
Requires-Dist: uvicorn[standard]>=0.34.3
